Metadata-Version: 2.1
Name: pyrepresent
Version: 0.4.0
Summary: A module for object and model representations as strings, with vast configurations, colors, hidden and protected values, assignment operations, memory addresses and more.
Home-page: https://github.com/Shahaf-F-S/represent
Author: Shahaf Frank-Shapir
Author-email: shahaffrs@gmail.com
License: MIT
Classifier: Intended Audience :: Developers
Classifier: License :: OSI Approved :: MIT License
Classifier: Programming Language :: Python
Classifier: Programming Language :: Python :: 3
Classifier: Programming Language :: Python :: 3.8
Classifier: Programming Language :: Python :: 3.9
Classifier: Programming Language :: Python :: 3.10
Classifier: Programming Language :: Python :: 3.11
Classifier: Operating System :: OS Independent
Provides-Extra: dev
